nonebot_plugin_read_60s/__init__.py
nonebot_plugin_read_60s/config.py
nonebot_plugin_read_60s-0.2.3.dist-info/METADATA
nonebot_plugin_read_60s-0.2.3.dist-info/WHEEL
nonebot_plugin_read_60s-0.2.3.dist-info/top_level.txt
nonebot_plugin_read_60s-0.2.3.dist-info/RECORD
