Metadata-Version: 2.1
Name: nonebot-plugin-read-60s
Version: 0.2.3
Summary: time and path tool
Home-page: https://github.com/fengmm521/pipProject
Author: mage
Author-email: mage@woodcol.com
License: MIT Licence
Keywords: pip,pathtool,timetool,magetool,mage
Platform: any
